franklin_fastapi_extension/__init__.py
franklin_fastapi_extension/config/__init__.py
franklin_fastapi_extension/config/response_config.py
franklin_fastapi_extension/models/__init__.py
franklin_fastapi_extension/models/base.py
franklin_fastapi_extension/schemas/__init__.py
franklin_fastapi_extension/schemas/response.py
franklin_fastapi_extension/utils/__init__.py
franklin_fastapi_extension/utils/database_util.py
franklin_fastapi_extension/utils/jwt_util.py
franklin_fastapi_extension/utils/repository.py
franklin_fastapi_extension-1.2.1.dist-info/LICENSE
franklin_fastapi_extension-1.2.1.dist-info/METADATA
franklin_fastapi_extension-1.2.1.dist-info/WHEEL
franklin_fastapi_extension-1.2.1.dist-info/top_level.txt
franklin_fastapi_extension-1.2.1.dist-info/RECORD
