Metadata-Version: 2.1
Name: franklin_fastapi_extension
Version: 1.2.1
Summary: This is a FastAPI Extension to simplify the creation process of APIS
Home-page: https://github.com/franklinnevesfilho/franklin-fastapi-extension
Author: Franklin Neves Filho
License: WTFPL
Classifier: Programming Language :: Python :: 3
Classifier: Operating System :: OS Independent
Classifier: License :: Other/Proprietary License
Requires-Python: >=3.8
License-File: LICENSE
Requires-Dist: fastapi
Requires-Dist: uvicorn
Requires-Dist: sqlalchemy
Requires-Dist: mysql-connector-python
